{
  "title": "The Ultimate PDF Sharing Checklist  Sharing PDFs can be a breeze with Adobe Acrobat. Whether you're  ",
  "outline": [
    {
      "level": "title",
      "text": "collaborating on a project, seeking feedback, or simply distributing ",
      "page": 0,
      "top": 125.6,
      "sub_content": ""
    },
    {
      "level": "title",
      "text": "information, this checklist will ensure you cover all the bases. Let's dive ",
      "page": 0,
      "top": 146.4,
      "sub_content": ""
    },
    {
      "level": "title",
      "text": "into the essentials of sharing PDFs effectively. ",
      "page": 0,
      "top": 167.1,
      "sub_content": ""
    },
    {
      "level": "title",
      "text": "General Sharing Checklist ",
      "page": 0,
      "top": 195.9,
      "sub_content": ""
    },
    {
      "level": "title",
      "text": "Open Your PDF ",
      "page": 0,
      "top": 224.7,
      "sub_content": "•"
    },
    {
      "level": "title",
      "text": "Have you launched Acrobat or Acrobat Reader and opened ",
      "page": 0,
      "top": 253.6,
      "sub_content": "•"
    },
    {
      "level": "title",
      "text": "the PDF you want to share? ",
      "page": 0,
      "top": 274.4,
      "sub_content": ""
    },
    {
      "level": "title",
      "text": "Choose Your Sharing Method ",
      "page": 0,
      "top": 303.2,
      "sub_content": "•"
    },
    {
      "level": "title",
      "text": "Are you sharing via email, link, or a third-party app like ",
      "page": 0,
      "top": 332.0,
      "sub_content": "•"
    },
    {
      "level": "title",
      "text": "Microsoft Teams or WhatsApp? ",
      "page": 0,
      "top": 352.7,
      "sub_content": ""
    },
    {
      "level": "title",
      "text": "Set Permissions ",
      "page": 0,
      "top": 381.5,
      "sub_content": "•"
    },
    {
      "level": "title",
      "text": "Have you decided if recipients can comment or just view the ",
      "page": 0,
      "top": 410.4,
      "sub_content": "•"
    },
    {
      "level": "title",
      "text": "document? ",
      "page": 0,
      "top": 431.2,
      "sub_content": ""
    },
    {
      "level": "title",
      "text": "Add Recipients ",
      "page": 0,
      "top": 460.0,
      "sub_content": "•"
    },
    {
      "level": "title",
      "text": "Did you enter the email addresses of everyone who needs ",
      "page": 0,
      "top": 488.8,
      "sub_content": "•"
    },
    {
      "level": "title",
      "text": "access? ",
      "page": 0,
      "top": 509.5,
      "sub_content": ""
    },
    {
      "level": "title",
      "text": "Customize Your Message ",
      "page": 0,
      "top": 538.3,
      "sub_content": "•"
    },
    {
      "level": "title",
      "text": "Have you added a personal touch to the subject and message ",
      "page": 0,
      "top": 567.2,
      "sub_content": "•"
    },
    {
      "level": "title",
      "text": "fields? ",
      "page": 0,
      "top": 587.9,
      "sub_content": ""
    },
    {
      "level": "title",
      "text": "Create and Share the Link ",
      "page": 0,
      "top": 616.7,
      "sub_content": "•"
    },
    {
      "level": "title",
      "text": "Did you generate a shareable link and copy it for distribution? ",
      "page": 0,
      "top": 645.5,
      "sub_content": "•"
    },
    {
      "level": "title",
      "text": "Send the Invitation ",
      "page": 0,
      "top": 674.3,
      "sub_content": "•\nHave you sent the email or shared the link through your\n•"
    },
    {
      "level": "title",
      "text": "chosen platform? ",
      "page": 1,
      "top": 96.7,
      "sub_content": "Follow Up\n•\nAre you tracking who has accessed the document and\n•"
    },
    {
      "level": "title",
      "text": "following up as needed? ",
      "page": 1,
      "top": 175.1,
      "sub_content": "Professional Tip: Clear Instructions\nEnsure your email instructions are clear and concise to avoid any\nconfusion for your recipients.\nSharing Checklist for Real Estate Professionals\nIn the real estate industry, sharing documents efficiently is crucial for\nclosing deals and keeping clients informed. Here's a tailored checklist to\nhelp you manage your PDF sharing needs.\nReal Estate Sharing Checklist\nOpen Your Property Document\n•\nHave you launched Acrobat or Acrobat Reader and opened\n•\nthe property listing or contract you need to share?\nChoose Your Sharing Method\n•\nAre you sharing via email, link, or a third-party app like\n•"
    },
    {
      "level": "title",
      "text": "Microsoft Teams or WhatsApp? ",
      "page": 1,
      "top": 567.1,
      "sub_content": "Set Permissions\n•\nHave you decided if clients can comment on the document or\n•"
    },
    {
      "level": "title",
      "text": "just view it? ",
      "page": 1,
      "top": 645.5,
      "sub_content": "Add Clients and Stakeholders\n•\nDid you enter the email addresses of clients, agents, and other\n•"
    },
    {
      "level": "title",
      "text": "stakeholders? ",
      "page": 2,
      "top": 96.7,
      "sub_content": "Customize Your Message\n•\nHave you added a personal touch to the subject and message\n•"
    },
    {
      "level": "title",
      "text": "fields, highlighting key property details? ",
      "page": 2,
      "top": 175.1,
      "sub_content": "Create and Share the Link\n•\nDid you generate a shareable link and copy it for distribution?\n•\nSend the Invitation\n•\nHave you sent the email or shared the link through your\n•"
    },
    {
      "level": "title",
      "text": "chosen platform? ",
      "page": 2,
      "top": 311.1,
      "sub_content": "Follow Up\n•\nAre you tracking who has accessed the document and\n•\nfollowing up with clients for feedback or next steps?\nProfessional Tip: Highlight Key Details\nMake sure to emphasize important property details in your message to\ncapture your clients' attention.\nConclusion\nSharing PDFs with Adobe Acrobat is straightforward and efficient,\nwhether you're working on a general project or managing real estate\ndocuments. By following these checklists, you can ensure that your\nsharing process is smooth and professional. Start sharing smarter today."
    }
  ]
}